{
	"name":"hotels",
	"fields":[
	   {
		  "name":"HotelId",
		  "type":"Edm.String",
		  "key":true,
		  "facetable":true,
		  "filterable":true,
		  "retrievable":true,
		  "searchable":true,
		  "sortable":true
	   },
	   {
		  "name":"HotelName",
		  "type":"Edm.String",
		  "facetable":false,
		  "filterable":false,
		  "retrievable":true,
		  "searchable":true,
		  "sortable":true
	   },
	   {
		  "name":"Description",
		  "type":"Edm.String",
		  "facetable":false,
		  "filterable":false,
		  "retrievable":true,
		  "searchable":true,
		  "sortable":false,
		  "analyzer":"en.lucene"
	   },
	   {
		  "name":"Description_fr",
		  "type":"Edm.String",
		  "facetable":false,
		  "filterable":false,
		  "retrievable":true,
		  "searchable":true,
		  "sortable":false,
		  "analyzer":"fr.lucene"
	   },
	   {
		  "name":"Category",
		  "type":"Edm.String",
		  "facetable":true,
		  "filterable":true,
		  "retrievable":true,
		  "searchable":true,
		  "sortable":true
	   },
	   {
		  "name":"Tags",
		  "type":"Collection(Edm.String)",
		  "facetable":true,
		  "filterable":true,
		  "retrievable":true,
		  "searchable":true,
		  "sortable":false
	   },
	   {
		  "name":"ParkingIncluded",
		  "type":"Edm.Boolean",
		  "facetable":true,
		  "filterable":true,
		  "sortable":true,
		  "retrievable":true
	   },
	   {
		  "name":"LastRenovationDate",
		  "type":"Edm.DateTimeOffset",
		  "facetable":true,
		  "filterable":true,
		  "retrievable":true,
		  "sortable":true
	   },
	   {
		  "name":"Rating",
		  "type":"Edm.Double",
		  "facetable":true,
		  "filterable":true,
		  "sortable":true,
		  "retrievable":true
	   },
	   {
		  "name":"Address",
		  "type":"Edm.ComplexType",
		  "fields":[
			 {
				"name":"StreetAddress",
				"type":"Edm.String",
				"facetable":false,
				"filterable":false,
				"retrievable":true,
				"searchable":true,
				"sortable":false
			 },
			 {
				"name":"City",
				"type":"Edm.String",
				"facetable":true,
				"filterable":true,
				"retrievable":true,
				"searchable":true,
				"sortable":true
			 },
			 {
				"name":"StateProvince",
				"type":"Edm.String",
				"facetable":true,
				"filterable":true,
				"retrievable":true,
				"searchable":true,
				"sortable":true
			 },
			 {
				"name":"PostalCode",
				"type":"Edm.String",
				"facetable":true,
				"filterable":true,
				"retrievable":true,
				"searchable":true,
				"sortable":true
			 },
			 {
				"name":"Country",
				"type":"Edm.String",
				"facetable":true,
				"filterable":true,
				"retrievable":true,
				"searchable":true,
				"sortable":true
			 }
		  ]
	   },
	   {
		  "name":"Location",
		  "type":"Edm.GeographyPoint",
		  "filterable":true,
		  "retrievable":true,
		  "sortable":true
	   },
	   {
		  "name":"Rooms",
		  "type":"Collection(Edm.ComplexType)",
		  "fields":[
			 {
				"name":"Description",
				"type":"Edm.String",
				"facetable":false,
				"filterable":false,
				"retrievable":true,
				"searchable":true,
				"sortable":false,
				"analyzer":"en.lucene"
			 },
			 {
				"name":"Description_fr",
				"type":"Edm.String",
				"facetable":false,
				"filterable":false,
				"retrievable":true,
				"searchable":true,
				"sortable":false,
				"analyzer":"fr.lucene"
			 },
			 {
				"name":"Type",
				"type":"Edm.String",
				"facetable":true,
				"filterable":true,
				"retrievable":true,
				"searchable":true
			 },
			 {
				"name":"BaseRate",
				"type":"Edm.Double",
				"facetable":true,
				"filterable":true,
				"retrievable":true
			 },
			 {
				"name":"BedOptions",
				"type":"Edm.String",
				"facetable":true,
				"filterable":true,
				"retrievable":true,
				"searchable":true,
				"sortable":false
			 },
			 {
				"name":"SleepsCount",
				"type":"Edm.Int32",
				"facetable":true,
				"filterable":true,
				"retrievable":true,
				"sortable":false
			 },
			 {
				"name":"SmokingAllowed",
				"type":"Edm.Boolean",
				"facetable":true,
				"filterable":true,
				"retrievable":true,
				"sortable":false
			 },
			 {
				"name":"Tags",
				"type":"Collection(Edm.String)",
				"facetable":true,
				"filterable":true,
				"retrievable":true,
				"searchable":true
			 }
		  ]
	   }
	],
	"suggesters":[
	   {
		  "name":"sg",
		  "searchMode":"analyzingInfixMatching",
		  "sourceFields":[
			 "HotelName"
		  ]
	   }
	],
	"scoringProfiles":[
	   {
		  "name":"boostByField",
		  "functions":[
			 
		  ],
		  "functionAggregation":null,
		  "text":{
			 "weights":{
				"Tags":3,
				"HotelName":2,
				"Description":1.5,
				"Description_fr":1.5
			 }
		  }
	   },
	   {
		  "name":"boostAmenities",
		  "functions":[
			 {
				"fieldName":"Tags",
				"freshness":null,
				"interpolation":"linear",
				"magnitude":null,
				"distance":null,
				"tag":{
				   "tagsParameter":"amenities"
				},
				"type":"tag",
				"boost":5
			 }
		  ],
		  "functionAggregation":0
	   },
	   {
		  "name":"renovatedAndHighlyRated",
		  "functions":[
			 {
				"fieldName":"Rating",
				"freshness":null,
				"interpolation":"linear",
				"magnitude":{
				   "boostingRangeStart":0,
				   "boostingRangeEnd":5,
				   "constantBoostBeyondRange":false
				},
				"distance":null,
				"tag":null,
				"type":"magnitude",
				"boost":20
			 },
			 {
				"fieldName":"LastRenovationDate",
				"freshness":{
				   "boostingDuration":"P730D"
				},
				"interpolation":"quadratic",
				"magnitude":null,
				"distance":null,
				"tag":null,
				"type":"freshness",
				"boost":10
			 }
		  ],
		  "functionAggregation":0
	   }
	],
	"defaultScoringProfile":"boostByField",
	"corsOptions":{
	   "allowedOrigins":[
		  "*"
	   ],
	   "maxAgeInSeconds":null
	},
	"analyzers":[
	   
	],
	"charFilters":[
	   
	],
	"tokenFilters":[
	   
	],
	"tokenizers":[
	   
	],
	"similarity":{
	   "@odata.type":"#Microsoft.Azure.Search.ClassicSimilarity"
	},
	"encryptionKey":null,
	"@odata.etag":"\"0x8D842F5970E055B\""
 }